tests/__init__.py
tests/test_basic.py
traauto/__init__.py
traauto/tra.py
traauto-0.1.0.dist-info/LICENSE
traauto-0.1.0.dist-info/METADATA
traauto-0.1.0.dist-info/WHEEL
traauto-0.1.0.dist-info/top_level.txt
traauto-0.1.0.dist-info/RECORD
