Metadata-Version: 2.1
Name: traauto
Version: 0.1.0
Summary: AutoML with Enhanced Track-Rail Algorithm, meta-learning, feature engineering, explainability, and smart ensemble fusion.
Home-page: https://github.com/eswaroy/automl_tra
Author: Dasari Ranga Eswar
Author-email: Dasari Ranga Eswar <rangaeswar890@gmail.com>
License: MIT
Classifier: Programming Language :: Python :: 3.7
Classifier: Programming Language :: Python :: 3.8
Classifier: Programming Language :: Python :: 3.9
Classifier: Programming Language :: Python :: 3.10
Classifier: Operating System :: OS Independent
Classifier: License :: OSI Approved :: MIT License
Requires-Python: >=3.7
License-File: LICENSE
Requires-Dist: numpy
Requires-Dist: pandas
Requires-Dist: scikit-learn
Requires-Dist: joblib
Requires-Dist: psutil
Provides-Extra: imblearn
Requires-Dist: imbalanced-learn; extra == "imblearn"
Provides-Extra: lightgbm
Requires-Dist: lightgbm; extra == "lightgbm"
Provides-Extra: lime
Requires-Dist: lime; extra == "lime"
Provides-Extra: optuna
Requires-Dist: optuna>=2.0.0; extra == "optuna"
Provides-Extra: shap
Requires-Dist: shap; extra == "shap"
Provides-Extra: torch
Requires-Dist: torch; extra == "torch"
Provides-Extra: xgboost
Requires-Dist: xgboost; extra == "xgboost"
